{
  "NewsItems": {
    "title": "Nachrichten",
    "screen": "Index",
    "query": "newsItems",
    "queryVariables": {}
  },
  "PointsOfInterest": {
    "title": "Orte & Routen",
    "screen": "Index",
    "query": "pointsOfInterest",
    "queryVariables": {}
  },
  "EventRecords": {
    "title": "Veranstaltungen",
    "screen": "Index",
    "query": "eventRecords",
    "queryVariables": {}
  },
  "Mitmachen": {
    "title": "Mitmachen",
    "screen": "Html",
    "query": "publicHtmlFile",
    "queryVariables": {
      "name": "mitmachen"
    },
    "subQuery": "false"
  },
  "Service": {
    "title": "Service",
    "screen": "Html",
    "query": "publicHtmlFile",
    "queryVariables": {
      "name": "service"
    },
    "subQuery": "false"
  },
  "Feedback": {
    "title": "Feedback",
    "screen": "Html",
    "query": "publicHtmlFile",
    "queryVariables": {
      "name": "feedback"
    },
    "rootRouteName": "Feedback",
    "subQuery": {
      "routeName": "Web",
      "buttonTitle": "zum Feedback-Formular",
      "webUrl": "https://smart-village.app/feedback"
    }
  },
  "Datenschutz": {
    "title": "Datenschutz",
    "screen": "Html",
    "query": "publicHtmlFile",
    "queryVariables": {
      "name": "datenschutz"
    },
    "subQuery": "false"
  },
  "Impressum": {
    "title": "Impressum",
    "screen": "Html",
    "query": "publicHtmlFile",
    "queryVariables": {
      "name": "impressum"
    },
    "subQuery": "false"
  }
}
